Workbook

Sheet Planilha1
A1: Cargo | B1: Situação | C1: Código FOPAG | D1: Tipo de Provimento | E1: Recrutamento | F1: Restrição - Exigência | G1: Carga Horária Semanal | H1: Fonte Carga Horária | I1: Símbolo de Vencimento | J1: Total de cargos PREVISTOS | K1: Total de cargos OCUPADOS | L1: SALDO TOTAL | M1: Atribuições | N1: 813/99 - Plano de cargos, vencimentos e carreiras do servidores públicos | O1: 824/00 | P1: 827/00 | Q1: 845/00 | R1: 846/00 - Disciplina o regime de emprego público de pessoal da UTIL | S1: 851/01 | T1: 867/01 | U1: 924/01 - Concurso | V1: 926/02 | W1: 929/02 | X1: 933/02 | Y1: 944/02 | Z1: 984/03 | AA1: 985/03 | AB1: 994/03 | AC1: 1004/03 - Concurso | AD1: 1013/03 - Cria Conselho Tutelar | AE1: 1015/03 | AF1: 1017/03 - Plano de Cargos, Vencimentos e Carreiras da CAPPS | AG1: 1019/03 | AH1: 1027/03 | AI1: 1034/04 | AJ1: 1058/04 | AK1: 1073/04 (Verificar) | AL1: 1075/04 | AM1: 1079/04 | AN1: 1085/05 | AO1: 1090/05 | AP1: 1162/07 - Extinção da UTIL; Quadro de pessoal se constitui em quadro suplementar da Sec. Mun. De Obras; | AQ1: 1165/07 - Conselho Tutelar | AR1: 1167/07 | AS1: 1169/07 (Verificar) | AT1: 1175/07 (Art. 2º revogado pela Lei 1786/18) | AU1: 1190/08 | AV1: 1202/08 | AW1: 1206/08 | AX1: 1209/08 | AY1: 1223/08 | AZ1: 1230/08 - Quadro complementar de quadros em extinção | BA1: 1232/08 | BB1: 1233/08 - Altera as Leis nº 718/1998 e 846/2000 | BC1: 1241/08 - Cria DPCA da Guarda Municipal | BD1: 1244/08 - Carga horária Médico Veterinário e Pedagogo | BE1: 1260/09 | BF1: 1261/09 | BG1: 1272/09 (art. 2º revogado pela Lei nº 2158/2024) | BH1: 1278/09 (Revogada parcialmente pela Lei 1625/15) | BI1: 1285/09 | BJ1: 1299/10 | BK1: 1307/10 | BL1: 1309/10 | BM1: 1311/10 (Art. 2º revogado pela Lei 1786/18) | BN1: 1317/10 | BO1: 1318/10 | BP1: 1340/10 | BQ1: 1341/10 | BR1: 1343/10 | BS1: 1344/10 | BT1: 1346/10 | BU1: 1362/11 | BV1: 1363/11 | BW1: 1364/11 | BX1: 1365/11 | BY1: 1367/11 - Revoga a Lei 699/98; Plano de Carreira e Remuneração do Magistério; Revogada pela Lei 1808/18 | BZ1: 1375/11 | CA1: 1376/11 - Extingue Sec. Mun. De Segurança Pública; Revoga Lei 1317/10 | CB1: 1377/11 | CC1: 1386/12 | CD1: 1391/12 | CE1: 1392/12 | CF1: 1394/12 | CG1: 1395/12 | CH1: 1396/12 | CI1: 1399/12 | CJ1: 1404/12 | CK1: 1405/12 | CL1: 1406/12 - Regimento Interno CGM | CM1: 1411/12 | CN1: 1416/12 | CO1: 1419/13 | CP1: 1422/13 | CQ1: 1423/13 | CR1: 1424/13 | CS1: 1427/13 | CT1: 1428/13 (Revogada pela Lei nº 2163/2024 | CU1: 1430/13 | CV1: 1431/13 | CW1: 1432/13 | CX1: 1433/13 (Revogada pela Lei 1786/18) | CY1: 1434/13 | CZ1: 1440/13 | DA1: 1443/13 | DB1: 1448/13 | DC1: 1449/13 | DD1: 1450/13 | DE1: 1451/13 | DF1: 1452/13 | DG1: 1459/13 | DH1: 1460/13 - Reestrutura Lei 1017/03 (CAPPS) | DI1: 1461/13 - Controle Interno CAPPS | DJ1: 1465/13 - Revogada parcialmente pela Lei 1632/16 | DK1: 1466/13 - Concurso CAPS | DL1: 1468/13 | DM1: 1495/14 | DN1: 1524/14 | DO1: 1526/14 | DP1: 1527/14 | DQ1: 1528/14 (Revogada pela Lei 1598/15; Revogada pela Lei 1786/18) | DR1: 1555/14 | DS1: 1563/14 | DT1: 1580/15 | DU1: 1598/15 (Revogada pela Lei nº 2158/2024) | DV1: 1599/15 | DW1: 1600/15 | DX1: 1604/15 | DY1: 1605/15 | DZ1: 1608/15 - Altera de Auditor para Auditor Fiscal | EA1: 1617/15 - Altera Lei 1604/15 | EB1: 1618/15 - Altera Anexo I Lei 1367/11; Revogada pela Lei 1808/18 | EC1: 1625/16 - Revoga parcialmente Lei 1278/09; Altera de Auditor para Auditor Fiscal | ED1: 1632/16 - Plano de Cargos, Carreiras e Salários ACE e ACS; Alterada pela Lei 1814/19 | EE1: 1637/16 | EF1: 1643/16 | EG1: 1659/16 | EH1: 1662/16 | EI1: 1664/16 - Estatuto da Guarda Civil de Miracema, o Plano de Cargos e Carreira, Regimento Interno | EJ1: 1680/16 | EK1: 1687/16 | EL1: 1688/17 | EM1: 1704/17 | EN1: 1707/17 | EO1: 1708/17 | EP1: 1715/17 | EQ1: 1727/17 - Reestrutura RPPS | ER1: 1731/17 | ES1: 1732/17 | ET1: 1733/17 | EU1: 1743/17 - Reestrutura a S. M. de Licitação e Compras; Altera para S. M. de Licitação, Compras e Contratos; Revogada pela Lei nº 2158/2024 | EV1: 1749/17 | EW1: 1750/17 | EX1: 1768/18 | EY1: 1772/18 | EZ1: 1786/18 - Revoga Leis 1433/13, 1528/14, 1311/10 (art. 2º), 1175/07 (art. 2º) | FA1: 1796/18 - Reduz carga horária de Zootecnista | FB1: 1798/18 - Altera Lei 1664/16 | FC1: 1799/18 | FD1: 1800/18 - Altera Lei 1608/15 | FE1: 1808/18 - Reformulação, implantação e gestão do Plano de Carreira do Magistério Público Municipal de Miracema | FF1: 1809/18 - Reestruturação dos cargos de Fiscal de Tributos, Técnico de Tributação e Auxiliar de Tributação | FG1: 1813/19 - Reestrutura RPPS | FH1: 1814/19 - Regulamenta Lei Federal nº 13.708/18, alterando a Lei Municipal nº 1632/16 - ACS e ACE | FI1: 1823/19 | FJ1: 1825/19 | FK1: 1840/19 - Plano de Carreira, Cargos e Remuneração - Fiscal de Tributos, Analista Tributário e Agente Tributário | FL1: 1857/19 | FM1: 1858/19 | FN1: 1863/19 - Plano de Carreira, Cargos e Remuneração - S. M. Obras e Transporte e S. M. Meio Ambiente | FO1: 1864/19 | FP1: 1868/20 - Estatuto da Guarda Civil de Miracema, o Plano de Cargos e Carreira, Regimento Interno | FQ1: 1873/19 | FR1: 1884/20 - Plano de carreira e vencimentos da Área de Tecnologia da Informação | FS1: 1885/20 - Plano de carreira e vencimentos de Auxiliar de Administração | FT1: 1886/20 - Reenquadramento por transposição de regime jurídico do pessoal da UTIL | FU1: 1887/20 | FV1: 1888/20 - Altera remuneração de Auxiliar de Saúde Bucal e Auxiliar de Material | FW1: 1889/20 | FX1: 1934/21 | FY1: 1935/21 | FZ1: 1957/21 | GA1: 1960/21 | GB1: 1999/21 | GC1: 2000/21 | GD1: 2001/21 | GE1: 2009/22 | GF1: 2014/22 | GG1: 2029/22 - Implantação do Vencimento Básico dos Agentes Comunitários de Saúde e Agentes de Combate às Endemias | GH1: 2035/22 | GI1: 2036/22 | GJ1: 2041/22 - Plano de Carreira, Cargos e Remuneração - Jardineiros, Garis, Coveiros e Auxiliar de Arquivo | GK1: 2042/22 - Plano de Carreira, Cargos e Remuneração - Ajudante de Obras e Serviços | GL1: 2043/22 - Plano de Carreira, Cargos e Remuneração - Economista | GM1: 2050/22 | GN1: 2051/22 | GO1: 2053/22 - Plano de Carreira, Cargos e Remuneração - Auxiliar de Saúde, Auxiliar de Enfermagem e Auxiliar de Laboratório | GP1: 2058/22 - Moderniza, regulamenta a estrutura e as atribuições do Departamento de Recursos Humanos e do Departamento de Registro de Pagamento e Pessoal (Revogada pela Lei nº 2163/2024) | GQ1: 2064/22 | GR1: 2065/22 - Altera Lei 2043/22 (Economista) | GS1: 2066/22 | GT1: 2067/22 - Regulamenta a carga horária de Farmacêutico e Auxiliar de Laboratório | GU1: 2068/22 - Plano de Carreira, Cargos e Remuneração - Secretário Escolar | GV1: 2069/22 - Plano de Carreira, Cargos e Remuneração - Pedagogo | GW1: 2070/22 - Altera as Leis 1809/18, 1840/19, 813/99, 798/99 | GX1: 2092/23 | GY1: 2096/23 - Regulamenta o vencimento dos Servidores Municipais que possuem estabilidade excepcional garantida pelo art. 19 do ADCT | GZ1: 2110/23 - Plano de Carreira e Vencimentos de Técnico de Administração e Contador | HA1: 2117/23 - Altera Lei 1884/20 | HB1: 2122/23 - Extingue 1 cargo de Assessor (S. M Governo) e cria 1 cargo de Responsável pela Supervisão e Fiscalização dos Serviços de Varrição de Vias e Logradouros Públicos (S. M. Meio Ambiente) | HC1: 2139/23 - Plano de Carreira e Vencimentos de Enfermeiro, Técnico de Enfermagem e Fonoaudiólogo | HD1: 2140/23 - Plano de Carreira e Vencimentos de Motorista, Operador de Máquinas Pesadas e Motorista de Ambulância | HE1: 2141/23 - Plano de Carreira e Vencimentos de Cantineiro Escolar, Servente Escolar e Contínuo-Servente | HF1: 2142/23 - Plano de Carreira e Vencimentos de Médico Veterinário, Biólogo, Técnico Agrícola e Auxiliar de Biblioteca | HG1: 2143/23 - Plano de Carreira e Vencimentos de Instrutor Oficineiro e Cozinheiro | HH1: 2144/23 - Plano de Carreira e Vencimentos Técnico em Saúde Bucal e Auxiliar em Saúde Bucal | HI1: 2148/23 - Plano de Carreira e Vencimentos do Quadro da UTIL (não optantes) | HJ1: 2149/24 - Altera Lei 1868/19 (Guarda Municipal) | HK1: 2154/2024 - reestruturação de carreiras do Poder Executivo, instituindo o Plano de Carreira, Cargos e Remuneração | HL1: 2158/2024 - Estruturação e modernização da Secretaria de Licitação, Compras e Contratos Revoga as Leis nº 1743/2017, 1598/2015, 1272/2009 (art. 2º) | HM1: 2159/2024 - Regulamenta a carga horaria Fonoaudiólogo | HN1: 2163/2024 - Regulamenta a estrutura e as atribuições da Coordenadoria Geral de Recursos Humanos e do Coordenadoria Geral de Registro de Pagamento e Pessoal (Revoga as Leis nº 1428/2013 e 2058/2022) | HO1: 2169/2024 - Criação do Fundo Municipal de Educação - FME | HP1: 2189/2024 - Regulamenta a carga horaria Assistente Social e Massoterapeuta | HQ1: 2194/2024 - Cria cargos ACS | HR1: 2196/2024 - Retifica art. 1 da Lei 2194/2024 | HS1: Coluna1 | HT1: 2287/26 - Cria 1 cargo | HU1: Lei nº 2.275/2026
A2: Advogado do Centro de Referência Especializada de Assistência Social | B2: Em vigor | C2: 409 | D2: Efetivo | F2: Superior | G2: 20 | H2: Edital 2023 - BO 375 | I2: P-34 | J2: 1 | K2: 1 | L2: =Planilha1!$J2-Planilha1!$K2 -> 0 | M2: Lei complementar Municipal Nº 1465/2013 - Art. 30, X | DJ2: Cria 1
A3: Agente Comunitário de Saúde - CEHAB | B3: Em vigor | C3: 1025 | D3: Efetivo | F3: Ensino Médio (Lei Federal nº 11.350/2006) | G3: 40 | H3: (Lei 1632/2016 e Lei Federal nº 13.708/18) | I3: P-I | J3: 6 | K3: 6 | L3: =Planilha1!$J3-Planilha1!$K3 -> 0 | M3: Lei ordinária Municipal Nº 1632/2016 - Art. 4º | DJ3: Cria 23; Edital Concurso 2014 distribui vagas. Art. 20 da Lei 1632/16 revoga art. 25 da Lei 1465/13, extinguindo as 23 vagas criadas pela Lei | ED3: Plano de Cargos, Carreiras e Salários; Anexo II cria 6, porém contanto com as vagas extintas. EDITAL Nº 09/ MIRACEMA / ENSINO FUNDAMENTAL / 22/07/2014, oferta 4 vagas, e até a publicação da Lei 1632/2016, nomeia 4 vagas para CEHAB. Conclui-se que fixa 4 vagas | EF3: Cria +1; Totaliza 5 | EG3: Cria +1; Totaliza 6 | FH3: Regulamenta Lei Federal nº 13.708/18, alterando a Lei Municipal nº 1632/16 | GG3: Implanta vencimento inicial
A4: Agente Comunitário de Saúde - Cruzeiro | B4: Em vigor | C4: 1026 | D4: Efetivo | F4: Ensino Médio (Lei Federal nº 11.350/2006) | G4: 40 | H4: (Lei 1632/2016 e Lei Federal nº 13.708/18) | I4: P-I | J4: 5 | K4: 4 | L4: =Planilha1!$J4-Planilha1!$K4 -> 1 | M4: Lei ordinária Municipal Nº 1632/2016 - Art. 4º | DJ4: Cria 23; Edital Concurso 2014 distribui vagas. Art. 20 da Lei 1632/16 revoga art. 25 da Lei 1465/13, extinguindo as 23 vagas criadas pela Lei | ED4: Plano de Cargos, Carreiras e Salários; Anexo II cria 4, porém contanto com as vagas extintas. EDITAL Nº 09/ MIRACEMA / ENSINO FUNDAMENTAL / 22/07/2014, oferta 3 vagas, e até a publicação da Lei 1632/2016, nomeia 3 vagas para Cruzeiro. Conclui-se que fixa 3 vagas | EF4: Cria +1; Totaliza 4 | FH4: Regulamenta Lei Federal nº 13.708/18, alterando a Lei Municipal nº 1632/17 | HQ4: Cria +1; Totaliza 5
A5: Agente Comunitário de Saúde - Jardim Bervely | B5: Em vigor | C5: 1023 | D5: Efetivo | F5: Ensino Médio (Lei Federal nº 11.350/2006) | G5: 40 | H5: (Lei 1632/2016 e Lei Federal nº 13.708/18) | I5: P-I | J5: 0 | K5: 5 | L5: =Planilha1!$J6-Planilha1!$K6 -> -2 | M5: Lei ordinária Municipal Nº 1632/2016 - Art. 4º | DJ5: Cria 23; Edital Concurso 2014 distribui vagas. Art. 20 da Lei 1632/16 revoga art. 25 da Lei 1465/13, extinguindo as 23 vagas criadas pela Lei | ED5: Plano de Cargos, Carreiras e Salários; Anexo II cria 6, porém contanto com as vagas extintas. EDITAL Nº 09/ MIRACEMA / ENSINO FUNDAMENTAL / 22/07/2014, oferta 0 (CR) vagas, e até a publicação da Lei 1632/2016, nomeia 0 vagas para Jardim Bervely. Conclui-se que fixa 0 vagas | FH5: Regulamenta Lei Federal nº 13.708/18, alterando a Lei Municipal nº 1632/19
A6: Agente Comunitário de Saúde - Jove | B6: Em vigor | D6: Efetivo | F6: Ensino Médio (Lei Federal nº 11.350/2006) | G6: 40 | H6: (Lei 1632/2016 e Lei Federal nº 13.708/18) | I6: P-I | J6: 4 | K6: 6 | L6: =Planilha1!$J5-Planilha1!$K5 -> -5 | M6: Lei ordinária Municipal Nº 1632/2016 - Art. 4º | DJ6: Cria 23; Edital Concurso 2014 distribui vagas. Art. 20 da Lei 1632/16 revoga art. 25 da Lei 1465/13, extinguindo as 23 vagas criadas pela Lei | ED6: Plano de Cargos, Carreiras e Salários; Anexo II cria 4, porém contanto com as vagas extintas. EDITAL Nº 09/ MIRACEMA / ENSINO FUNDAMENTAL / 22/07/2014, oferta 3 vagas, e até a publicação da Lei 1632/2016, nomeia 2 vagas para Jove. Conclui-se que fixa 2 vagas | ES6: Cria +2; Totaliza 4 | FH6: Regulamenta Lei Federal nº 13.708/18, alterando a Lei Municipal nº 1632/18
A7: Agente Comunitário de Saúde - Nossa Senhora Aparecida | B7: Em vigor | C7: 1022 | D7: Efetivo | F7: Ensino Médio (Lei Federal nº 11.350/2006) | G7: 40 | H7: (Lei 1632/2016 e Lei Federal nº 13.708/18) | I7: P-I | J7: 7 | K7: 4 | L7: =Planilha1!$J7-Planilha1!$K7 -> 3 | M7: Lei ordinária Municipal Nº 1632/2016 - Art. 4º | DJ7: Cria 23; Edital Concurso 2014 distribui vagas. Art. 20 da Lei 1632/16 revoga art. 25 da Lei 1465/13, extinguindo as 23 vagas criadas pela Lei | ED7: Plano de Cargos, Carreiras e Salários; Anexo II cria 0. EDITAL Nº 09/ MIRACEMA / ENSINO FUNDAMENTAL / 22/07/2014, oferta 0 (CR) vagas, e até a publicação da Lei 1632/2016, nomeia 0 vagas para Nossa Senhora Aparecida. Conclui-se que fixa 0 vagas | ES7: Cria +4; Totaliza 4 | FH7: Regulamenta Lei Federal nº 13.708/18, alterando a Lei Municipal nº 1632/20 | HQ7: Cria +3; Totaliza 7
A8: Agente Comunitário de Saúde - Paraíso do Tobias | B8: Em vigor | C8: 1028 | D8: Efetivo | F8: Ensino Médio (Lei Federal nº 11.350/2006) | G8: 40 | H8: (Lei 1632/2016 e Lei Federal nº 13.708/18) | I8: P-I | J8: 5 | K8: 5 | L8: =Planilha1!$J8-Planilha1!$K8 -> 0 | M8: Lei ordinária Municipal Nº 1632/2016 - Art. 4º | DJ8: Cria 23; Edital Concurso 2014 distribui vagas. Art. 20 da Lei 1632/16 revoga art. 25 da Lei 1465/13, extinguindo as 23 vagas criadas pela Lei | ED8: Plano de Cargos, Carreiras e Salários; Anexo II cria 4, porém contanto com as vagas extintas. EDITAL Nº 09/ MIRACEMA / ENSINO FUNDAMENTAL / 22/07/2014, oferta 3 vagas, e até a publicação da Lei 1632/2016, nomeia 3 vagas para Paraíso do Tobias. Conclui-se que fixa 3 vagas | EG8: Cria +2; Totaliza 5 | FH8: Regulamenta Lei Federal nº 13.708/18, alterando a Lei Municipal nº 1632/21
A9: Agente Comunitário de Saúde - Pontilhão do Rosa | B9: Em vigor | C9: 1024 | D9: Efetivo | F9: Ensino Médio (Lei Federal nº 11.350/2006) | G9: 40 | H9: (Lei 1632/2016 e Lei Federal nº 13.708/18) | I9: P-I | J9: 1 | K9: 3 | L9: =Planilha1!$J9-Planilha1!$K9 -> -2 | M9: Lei ordinária Municipal Nº 1632/2016 - Art. 4º | DJ9: Cria 23; Edital Concurso 2014 distribui vagas. Art. 20 da Lei 1632/16 revoga art. 25 da Lei 1465/13, extinguindo as 23 vagas criadas pela Lei | ED9: Plano de Cargos, Carreiras e Salários; Anexo II cria 6, porém contanto com as vagas extintas. EDITAL Nº 09/ MIRACEMA / ENSINO FUNDAMENTAL / 22/07/2014, oferta 4 vagas, e até a publicação da Lei 1632/2016, nomeia 1 vagas paraPontilhão do Rosa. Conclui-se que fixa 1 vaga | FH9: Regulamenta Lei Federal nº 13.708/18, alterando a Lei Municipal nº 1632/22
A10: Agente Comunitário de Saúde - Venda das Flores | B10: Em vigor | C10: 1027 | D10: Efetivo | F10: Ensino Médio (Lei Federal nº 11.350/2006) | G10: 40 | H10: (Lei 1632/2016 e Lei Federal nº 13.708/18) | I10: P-I | J10: 1 | K10: 3 | L10: =Planilha1!$J10-Planilha1!$K10 -> -2 | M10: Lei ordinária Municipal Nº 1632/2016 - Art. 4º | DJ10: Cria 23; Edital Concurso 2014 distribui vagas. Art. 20 da Lei 1632/16 revoga art. 25 da Lei 1465/13, extinguindo as 23 vagas criadas pela Lei | ED10: Plano de Cargos, Carreiras e Salários; Anexo II cria 5, porém contanto com as vagas extintas. EDITAL Nº 09/ MIRACEMA / ENSINO FUNDAMENTAL / 22/07/2014, oferta 4 vagas, e até a publicação da Lei 1632/2016, nomeia 1 vaga paraVenda das Flores. Conclui-se que fixa 1 vaga | FH10: Regulamenta Lei Federal nº 13.708/18, alterando a Lei Municipal nº 1632/23
A11: Agente de Combate às Endemias | B11: Em vigor | C11: 165 | D11: Efetivo | F11: Ensino Médio (Lei Federal nº 11.350/2006) | G11: 40 | H11: (Lei 1632/2016 e Lei Federal nº 13.708/18) | I11: P-I | J11: 1 | K11: 14 | L11: =Planilha1!$J11-Planilha1!$K11 -> -13 | M11: Lei ordinária Municipal Nº 1632/2016 - Art. 5º | DJ11: Cria 13; Edital Concurso 2014 oferta 13 vagas. Art. 20 da Lei 1632/16 revoga art. 26 da Lei 1465/13, extinguindo as 13 vagas criadas pela Lei | ED11: Plano de Cargos, Carreiras e Salários; Trata como Agente de Combate às Endemias; Parágrafo único do art. 14 dispõe que ficam mantidas as 13 vagas criadas para o cargo, porém, considerando que o art. 26 da Lei revoga as vagas criadas, não há vagas a manter. Total 0 vagas | EF11: Cria +1; Totaliza 1 | ES11: Mantém 14, porém, deveria ser apenas 1 | FH11: Regulamenta Lei Federal nº 13.708/18, alterando a Lei Municipal nº 1632/16 | GG11: Implanta vencimento inicial
A12: Agente de Contratação - S. M. de Licitação, Compras e Contratos | B12: Em vigor | C12: 1318 | D12: Comissão | E12: Limitado | F12: Nível de escolaridade Superior | H12: Não definida em lei | I12: CC-2 | J12: 1 | K12: 1 | L12: =Planilha1!$J12-Planilha1!$K12 -> 0 | M12: 2158/2024 | HL12: Cria 2
A13: Agente de Defesa Civil | B13: Em vigor | C13: 1032 | D13: Efetivo | F13: Não regulamentada em lei | G13: Não regulamentada em lei | H13: Não regulamentada em lei | L13: =Planilha1!$J13-Planilha1!$K13 -> 0 | CO13: Cria 6
A14: Agente Tributário | B14: Em vigor | C14: 1192 | D14: Efetivo | F14: Ensino Médio | G14: 30 | I14: A-I | L14: =Planilha1!$J14-Planilha1!$K14 -> 0 | N14: Cria 5 | AR14: Totaliza 5 | CJ14: Cria +1; Totaliza 6 | CZ14: Cria +2; Totaliza 8 | FF14: Altera de Auxiliar de Tributação para Agente Tributário; Altera para Ensino Médio; Totaliza 7; Fixa a carga horária em 40h/semana | GW14: Fixa a carga horária em 30h/semana
A15: Ajudante de Obras e Serviços | B15: Em vigor | C15: 61 | D15: Efetivo | F15: Ensino Fundamental Incompleto | G15: Verificar edital | I15: A-I | L15: =Planilha1!$J15-Planilha1!$K15 -> 0 | N15: Cria 230 | T15: Aumenta para 250 | AR15: Totaliza 250 | FC15: Extingue 25 | FG15: Extingue 9 | FL15: Extingue 2 | FQ15: Extingue 14 | FW15: Extingue 9 | FX15: Extingue 1 | FY15: Extingue 1 | GF15: Extingue 8 | GK15: Plano de Carreira, Cargos e Remuneração; Altera símbolo de vencimento para A-I | HQ15: Extingue 14
A16: Ajudante de Obras e Serviços - UTIL | B16: Em vigor | C16: 152 | D16: Efetivo | F16: Ensino Fundamental Incompleto | G16: Verificar edital | I16: A-I | L16: =Planilha1!$J16-Planilha1!$K16 -> 0 | R16: Cria 100 | HI16: Plano de Carreira e Vencimentos; Altera atribuições; Altera de P-02 para A-I
A17: Analista da Corregedoria Geral do Município | B17: Em vigor | C17: 1311 | D17: Efetivo | F17: Superior - Direito | G17: 30 | I17: A-1 | L17: =Planilha1!$J17-Planilha1!$K17 -> 0 | GH17: Cria 2
A18: Analista de Tecnologia da Informação | B18: Em vigor | C18: 1204 | D18: Efetivo | F18: Superior | G18: 30 | I18: A-I | L18: =Planilha1!$J18-Planilha1!$K18 -> 0 | N18: Cria 1 | AR18: Totaliza 1 | BA18: Cria +1; Totaliza 2 | FR18: Extingue 1; Altera de Analista de Sistemas para Analista de Tecnologia da Informação; Fixa em 1; Altera de P-34 para A-I | HA18: Altera carga horária de 40 para 30 horas; altera GIDATI
A19: Analista Tributário | B19: Em vigor | C19: 1191 | D19: Efetivo | F19: Superior | G19: 30 | I19: A-I | L19: =Planilha1!$J19-Planilha1!$K19 -> 0 | N19: Cria 5 | AO19: Fixa em 5 | AR19: Totaliza 5 | FF19: Altera de Técnico de Tributação para Analista Tributário; Altera para Nível Superior; Fixa em 3; Fixa a carga horária em 40h/semana | GW19: Fixa a carga horária em 30h/semana
A20: Arquiteto | B20: Em vigor | C20: 1006 | D20: Efetivo | F20: Superior | G20: Verificar edital | I20: A-I | L20: =Planilha1!$J20-Planilha1!$K20 -> 0 | DJ20: Cria 1; Totaliza 1 | FN20: Plano de Carreira, Cargos e Remuneração; Dá atribuições; Altera de P-34 para A-I
A21: Arquivista | B21: Em vigor | C21: 197 | D21: Efetivo | F21: Superior | G21: Verificar edital | I21: P-34 | L21: =Planilha1!$J21-Planilha1!$K21 -> 0 | AR21: Cria 1; Totaliza 1
A22: Assessor | B22: Em vigor | D22: Comissão | E22: Amplo | I22: CC-3 | L22: =Planilha1!$J22-Planilha1!$K22 -> 0 | N22: Cria 2 | AO22: Fixa em 4 | CW22: Cria +1 (Planejamento e Desenvolvimento Econômico) | DW22: Cria +2 (Gabinete do Prefeito) | GF22: Extingue 1 | HB22: Extingue 1 (Sec. Mun. Governo)
A23: Assessor Administrativo do Auditório Cultural Clarinda Damasceno | B23: Em vigor | D23: Comissão | E23: - | I23: CC-3 | L23: =Planilha1!$J23-Planilha1!$K23 -> 0 | FE23: Cria 1
A24: Assessor CGM - Primeiro Assessor da Controladoria Geral (*) | B24: Em vigor | D24: Comissão | E24: Limitado - Quadro de Auditores Efetivos da CGM (*) | F24: Vide escolaridade de Auditor Fiscal (*) | I24: CC-2 | L24: =Planilha1!$J24-Planilha1!$K24 -> 0 | DN24: 1 (alterado de Diretor de Departamento de Auditoria, Controle, Fiscalização e Orientação dos Recursos do Fundeb e Programas da Educação)
A25: Assessor CGM - Segundo Assessor da Controladoria Geral (**) | B25: Em vigor | D25: Comissão | E25: Amplo (**) | F25: Superior + Registro no Conselho Regional (**) | I25: CC-2 | L25: =Planilha1!$J25-Planilha1!$K25 -> 0 | DN25: 1 (alterado de Diretor do Departamento de Auditoria, Controle, Orientação e Acompanhamento do SIGFIS e Prestações de Contas)
A26: Assessor CGM - Terceiro Assessor da Controladoria Geral (***) | B26: Em vigor | D26: Comissão | E26: Limitado (***) | F26: Superior (***) | I26: CC-2 | L26: =Planilha1!$J26-Planilha1!$K26 -> 0 | EO26: Cria +1
A27: Assessor da Secretaria de Licitação, Compras e Contratos | B27: Em vigor | C27: 1051 | D27: Comissão | E27: Limitado | F27: Superior em qualquer área | G27: Lei não informa | I27: CC-2 | L27: =Planilha1!$J27-Planilha1!$K27 -> 0 | EU27: Cria 1; Revogada pela Lei nº 2158/2024 | HL27: Cria 1
A28: Assessor de Acompanhamento e Lançamento de dados do CENSO, Bolsa Família e frequência da Secretaria Municipal de Educação, Esporte e Lazer | B28: Em vigor | C28: 1327 | D28: Comissão | E28: Amplo | F28: Não informado em lei | G28: Não informado em lei | I28: CC-3 | J28: 1 | K28: 0 | L28: =Planilha1!$J28-Planilha1!$K28 -> 1 | FX28: Cria 1
A29: Assessor de Apoio Administrativo da Secretaria Municipal de Educação, Esporte e Lazer | B29: Em vigor | C29: 1199 | D29: Comissão | E29: Limitado | I29: CC-3 | L29: =Planilha1!$J29-Planilha1!$K29 -> 0 | FQ29: Cria 1
A30: Assessor de Apoio Administrativo e Fomento ao Empreendedorismo | B30: Em vigor | D30: Comissão | E30: Amplo | I30: CC-3 | L30: =Planilha1!$J30-Planilha1!$K30 -> 0 | GB30: Cria 1
A31: Assessor de Apoio Fazendário da Secretaria Municipal de Fazenda | B31: Em vigor | C31: 1306 | D31: Comissão | E31: Restrito | F31: Não informado em lei | G31: Não informado em lei | I31: CC-3 | J31: 1 | K31: 0 | L31: =Planilha1!$J31-Planilha1!$K31 -> 1 | GW31: Cria 1
A32: Assessor de Eventos - S. M. Cultura e Turismo | B32: Em vigor | C32: 1333 | D32: Comissão | E32: Limitado | F32: Não informado em lei | G32: Não informado em lei | I32: CC-3 | J32: 1 | K32: 1 | L32: =Planilha1!$J32-Planilha1!$K32 -> 0 | GX32: Cria 1
A33: Assessor de Gabinete | B33: Em vigor | C33: 1056 | D33: Comissão | E33: Amplo | F33: Não informado em lei | G33: Não informado em lei | I33: CC-3 | J33: 1 | K33: 1 | L33: =Planilha1!$J33-Planilha1!$K33 -> 0 | M33: Lei ordinária Municipal Nº 1708/2017 | EO33: Cria 1
A34: Assessor de Geração de Trabalho e Renda, Qualificação e Orientação Profissional | B34: Em vigor | D34: Comissão | E34: Amplo | I34: CC-3 | L34: =Planilha1!$J34-Planilha1!$K34 -> 0 | GB34: Cria 1
A35: Assessor de Gestão da Secretaria Municipal de Saúde - S. M. Saúde | B35: Em vigor | D35: Comissão | E35: Amplo | I35: CC-3 | L35: =Planilha1!$J35-Planilha1!$K35 -> 0 | EO35: Cria 1
A36: Assessor de Jogos Coletivos e Modalidades Individuais | B36: Em vigor | D36: Comissão | E36: Amplo | I36: CC-3 | L36: =Planilha1!$J36-Planilha1!$K36 -> 0 | GC36: Cria 1
A37: Assessor de Procuradoria | B37: Em vigor | D37: Comissão | E37: Amplo | F37: Superior - Direito | I37: CC-2 | L37: =Planilha1!$J37-Planilha1!$K37 -> 0 | EZ37: Cria 4 | FM37: Divide em 1 SUAD, 2 SUCON, 1 SUFIT
A38: Assessor de Projetos da Secretaria Municipal de Obras, Urbanismo e Transporte - S. M. Obras, Urbanismo e Transporte | B38: Em vigor | D38: Comissão | E38: Amplo | I38: CC-3 | L38: =Planilha1!$J38-Planilha1!$K38 -> 0 | EO38: Cria 1
A39: Assessor de Publicação de Atos Oficiais | B39: Em vigor | D39: Comissão | E39: Amplo | I39: CC-3 | L39: =Planilha1!$J39-Planilha1!$K39 -> 0 | EO39: Cria 1 | ET39: Vincula ao Gabinete do Prefeito
A40: Assessor de Recursos Humanos* | B40: Em vigor | D40: Comissão | E40: Amplo* | F40: Ensino Médio | I40: CC-3 | L40: =Planilha1!$J40-Planilha1!$K40 -> 0 | GI40: Cria 1; Revogada pela Lei 2058/22 | GP40: Cria 2; Revogada pela Lei nº 2163/2024 | HN40: Cria 1
A41: Assessor de Recursos Humanos** | B41: Em vigor | C41: 1305 | D41: Comissão | E41: 4 vagas Limitado e 1 vaga amplo | F41: Ensino Médio de escolaridade | G41: Não informado em lei | I41: CC-3 | J41: 5 | K41: 4 | L41: =Planilha1!$J41-Planilha1!$K41 -> 1 | M41: Lei ordinária Municipal Nº 2163/2024 | HN41: Cria 5 – 1 vaga de recrutamento amplo e 4 vagas de recrutamento limitado
A42: Assessor de Registro de Pagamento e Pessoal | B42: Em vigor | C42: 1321 | D42: Comissão | E42: Limitado | F42: Ensino Médio | G42: Não informado em lei | I42: CC-3 | J42: 2 | K42: 2 | L42: =Planilha1!$J42-Planilha1!$K42 -> 0 | M42: Lei ordinária Municipal Nº 2163/2024 | HN42: Cria 2
A43: Assessor do Fundo Municipal de Assistência Social - S. M. Assistência Social | B43: Em vigor | C43: 1183 | D43: Comissão | E43: Amplo | F43: Não informado em lei | G43: Não informado em lei | I43: CC-3 | J43: 3 | K43: 3 | L43: =Planilha1!$J43-Planilha1!$K43 -> 0 | M43: Lei nº 1799/2018 | FC43: Cria 3
A44: Assessor Especial do Gabinete do Prefeito - S. M. Governo | B44: Em vigor | C44: 1188 | D44: Comissão | E44: Amplo | F44: Não informado em lei | G44: Não informado em lei | I44: CC-2 | J44: 2 | K44: 2 | L44: =Planilha1!$J44-Planilha1!$K44 -> 0 | M44: Lei nº 1799/2019 | FC44: Cria 1 | FQ44: Cria +1 | GF44: Cria +1 | HU44: Extingue 1 – Totaliza 2
A45: Assessor Fazendário - S. M. Fazenda | B45: Em vigor | C45: 1081 | D45: Comissão | E45: Amplo | F45: Não informado em lei | G45: Não informado em lei | I45: CC-3 | J45: 1 | K45: 1 | L45: =Planilha1!$J45-Planilha1!$K45 -> 0 | M45: Lei nº 1708/2017 | EO45: Cria 1
A46: Assessor Jurídico - Procuradoria Geral (EXTINTO) | B46: Extinto | D46: Comissão | E46: Amplo | I46: CC-2 | L46: =Planilha1!$J46-Planilha1!$K46 -> 0 | AT46: Cria 1; Revogada pela Lei 1786/18 | CX46: Cria +1; Totaliza 2; Revogadas pela Lei 1786/18 | DQ46: Cria +1; Revogada pela Lei 1598/15; Revogada pela Lei 1786/18 | DU46: Extingue; Revogada pela Lei nº 2158/2024
A47: Assessor Pedagógico do Auditório Cultural Clarinda Damasceno | B47: Em vigor | C47: 1193 | D47: Comissão | E47: Amplo | F47: Não informado em lei | G47: Não informado em lei | I47: CC-3 | J47: 1 | K47: 1 | L47: =Planilha1!$J47-Planilha1!$K47 -> 0 | M47: Não regulamentada em lei | FE47: Cria 1
A48: Assessor Superior do Gabinete do Prefeito | B48: Em vigor | C48: 146 | D48: Comissão | E48: Amplo | G48: Não informado em lei | I48: CC-1 | J48: 1 | K48: 1 | L48: =Planilha1!$J48-Planilha1!$K48 -> 0 | GD48: Cria 1
A49: Assessor Superior do Prefeito - Extinto | B49: Extinto | D49: Comissão | E49: - | G49: Não informado em lei | I49: CC-1 | L49: =Planilha1!$J49-Planilha1!$K49 -> 0 | AO49: Cria 1 | EO49: Extingue
A50: Assistente A da Coordenadoria Geral de Registro de Pagamento e Pessoal | B50: Em vigor | C50: 1322 | D50: Comissão | E50: Limitado | F50: Não informado em lei | G50: Não informado em lei | I50: CC-4 | J50: 2 | K50: 2 | L50: =Planilha1!$J50-Planilha1!$K50 -> 0 | HN50: Cria 2
A51: Assistente A da Coordenadoria Geral de RH | B51: Em vigor | C51: 1324 | D51: Comissão | E51: Limitado | F51: Não informado em lei | G51: Não informado em lei | I51: CC-4 | L51: =Planilha1!$J51-Planilha1!$K51 -> 0 | HN51: Cria 2
A52: Assistente A do Departamento de Registro de Pagamento e Pessoal (REVOGADO) | B52: Revogado | D52: Comissão | E52: Limitado | I52: CC-4 | L52: =Planilha1!$J52-Planilha1!$K52 -> 0 | GP52: Regulamenta; Cria 1; Revogada pela Lei nº 2163/2024
A53: Assistente A do Departamento de RH (REVOGADO) | B53: Revogado | D53: Comissão | E53: Limitado | I53: CC-4 | L53: =Planilha1!$J53-Planilha1!$K53 -> 0 | GP53: Regulamenta; Cria 1; Revogada pela Lei nº 2163/2024
A54: Assistente B da Coordenadoria Geral de RH | B54: Em vigor | D54: Comissão | E54: Limitado | I54: CC-5 | J54: 2 | K54: 2 | L54: =Planilha1!$J54-Planilha1!$K54 -> 0 | HN54: Cria 2
A55: Assistente B do Departamento de Registro de Pagamento e Pessoal (REVOGADO) | B55: Revogado | D55: Comissão | E55: Limitado | I55: CC-5 | L55: =Planilha1!$J55-Planilha1!$K55 -> 0 | GP55: Regulamenta; Cria 1; Revogada pela Lei nº 2163/2024
A56: Assistente B do Departamento de RH (REVOGADO) | B56: Revogado | D56: Comissão | E56: Limitado | I56: CC-5 | L56: =Planilha1!$J56-Planilha1!$K56 -> 0 | GP56: Regulamenta; Cria 1; Revogada pela Lei nº 2163/2024
A57: Assistente de Contratação - S. M. de Licitação, Compras e Contratos | B57: Em vigor | D57: Comissão | E57: Limitado | F57: Cargo efetivo Ensino Médio | I57: CC-4 | L57: =Planilha1!$J57-Planilha1!$K57 -> 0 | HL57: Cria 4
A58: Assistente de Encaminhamento do Expediente da Ouvidoria Geral | B58: Em vigor | C58: 1270 | D58: Comissão | E58: Limitado | F58: Não informado em lei | G58: Não informado em lei | I58: CC-5 | J58: 1 | K58: 1 | L58: =Planilha1!$J58-Planilha1!$K58 -> 0 | EX58: Cria 1
A59: Assistente Social | B59: Em vigor | D59: Efetivo | F59: Superior | G59: 20 | I59: A-I | L59: =Planilha1!$J59-Planilha1!$K59 -> 0 | N59: Cria 3 | V59: Cria +2 | Y59: Aumenta para 5 | AR59: Cria +1; Totaliza 6 | CI59: Cria +2 (CAPS); Totaliza 8 | DC59: Cria +4; Totaliza 11 | DE59: Cria +1; Totaliza 12 | DR59: Altera atribuições do cargo | EM59: Cria +5 | GQ59: Cria +3 | HK59: Plano de Carreira, Cargos e Remuneração; Dá atribuições; Altera de P-34 para A-I | HP59: Regulamenta carga horária em 20 horas/semana
A60: Auditor | B60: Em vigor | D60: Efetivo | F60: Superior | G60: Verificar edital | I60: P-34 | L60: =Planilha1!$J60-Planilha1!$K60 -> 0 | BH60: Cria 3 (1 Unidade de Controle e Fiscalização de Atos de Pessoal; 1 Unidade de Controle e Fiscalização de Licitações, Contratos e Convênios; 1 Unidade de Controle e Fiscalização Patrimonial e de Almoxarifado) | BZ60: Cria +2 (Unidade de Controle e Fiscalização Patrimonial e de Almoxarifado) | CE60: Cria +1 (Unidade de Controle e Fiscalização de Atos de Pessoal; Totaliza 2) | CJ60: Cria +4 (Unidade de Controle e Fiscalização de Licitações, Contratos e Convênios) | DZ60: Altera para Auditor Fiscal - Área Recursos Humanos, Auditor Fiscal - Área de Licitações, Contratos e Convênios, Auditor Fiscal - Área Patrimônio e Almoxarifado | EC60: Altera para Auditor Fiscal - Área Recursos Humanos, Auditor Fiscal - Área de Licitações, Contratos e Convênios, Auditor Fiscal - Área Patrimônio e Almoxarifado
A61: Auditor e Presidente do Controle Interno (revogado) | B61: Revogado | D61: Comissão | E61: Amplo | I61: CC-1 | L61: =Planilha1!$J61-Planilha1!$K61 -> 0 | S61: Cria 1
A62: Auditor Fiscal - Área Contábil | B62: Em vigor | D62: Efetivo | F62: Superior - Ciências Contábeis | G62: 20 | I62: A-I | L62: =Planilha1!$J62-Planilha1!$K62 -> 0 | BH62: Cria 1 (Unidade de Controle e Fiscalização Contábil, Tributária, Orçamentária e Financeira) | BZ62: Cria +2 (Unidade de Controle e Fiscalização Contábil, Tributária, Orçamentária e Financeira) | DZ62: Alterado de Auditor Contábil para Auditor Fiscal - Área Contábil; 3 cargos | EC62: Alterado de Auditor Contábil para Auditor Fiscal - Área Contábil | FD62: Extingue 1; Totaliza 2 | GE62: Altera carga horária de 30h/semana para 20h/semana
A63: Auditor Fiscal - Área de Enfermagem | B63: Em vigor | D63: Efetivo | F63: Superior - Enfermagem; Especialista em Auditoria; registro no respectivo Conselho ou Órgão Fiscalizador do Exercício da Profissão | G63: 20 | I63: A-I | L63: =Planilha1!$J63-Planilha1!$K63 -> 0 | GE63: Cria 1; Altera carga horária de 30h/semana para 20h/semana
A64: Auditor Fiscal - Área Fazendária | B64: Em vigor | D64: Efetivo | F64: Superior - Direito ou Contabilidade | G64: 20 | I64: A-I | L64: =Planilha1!$J64-Planilha1!$K64 -> 0 | DZ64: Cria 1 (Redistribuído de Auditor de Licitações, Contratos e Convênios) | GE64: Altera carga horária de 30h/semana para 20h/semana; Dá atribuições
A65: Auditor Fiscal - Área Licitações, Contratos e Convênios | B65: Em vigor | D65: Efetivo | F65: Superior - Direito | G65: 20 | I65: A-I | L65: =Planilha1!$J65-Planilha1!$K65 -> 0 | DZ65: Alterado de Auditor de Licitações, Contratos e Convênios para Auditor Fiscal - Área Licitações, Contratos e Convênios; 4 cargos | EC65: Alterado de Auditor de Licitações, Contratos e Convênios Auditor Fiscal - Área Licitações, Contratos e Convênios | GE65: Altera carga horária de 30h/semana para 20h/semana
A66: Auditor Fiscal - Área Obras Públicas | B66: Em vigor | D66: Efetivo | F66: Superior - Engenharia Civil | G66: 20 | I66: A-I | L66: =Planilha1!$J66-Planilha1!$K66 -> 0 | BH66: Cria 1 (Unidade de Controle e Fiscalização de Obras Públicas) | DZ66: Alterado de Auditor de Obras Públicas (Unidade de Controle e Fiscalização de Obras Públicas) para Auditor Fiscal - Área Obras Públicas; 1 cargo | EC66: Alterado de Auditor de Obras Públicas para Auditor Fiscal - Área Obras Públicas | GE66: Altera carga horária de 30h/semana para 20h/semana
A67: Auditor Fiscal - Área Patrimônio e Almoxarifado | B67: Em vigor | D67: Efetivo | F67: Superior - Ciências Contábeis | G67: 20 | I67: A-I | L67: =Planilha1!$J67-Planilha1!$K67 -> 0 | DZ67: Alterado de Auditor de Patrimônio e Almoxarifado para Auditor Fiscal - Área Patrimônio e Almoxarifado; 3 cargos | EC67: Alterado de Auditor de Patrimônio e Almoxarifado para Auditor Fiscal - Área Patrimônio e Almoxarifado | GE67: Altera carga horária de 30h/semana para 20h/semana
A68: Auditor Fiscal - Área Recursos Humanos | B68: Em vigor | D68: Efetivo | F68: Superior | G68: 20 | I68: A-I | L68: =Planilha1!$J68-Planilha1!$K68 -> 0 | DZ68: Alterado de Auditor de Recursos Humanos para Auditor Fiscal - Área Recursos Humanos; 2 cargos | EC68: Alterado de Auditor de Recursos Humanos para Auditor Fiscal - Área Recursos Humanos | FD68: Cria +1; Totaliza 3 | GE68: Altera carga horária de 30h/semana para 20h/semana
A69: Auxiliar Administrativo - CAPPS | B69: Em vigor | D69: Efetivo | F69: Ensino Fundamental | L69: =Planilha1!$J69-Planilha1!$K69 -> 0 | AV69: Aumenta para 6 | DK69: Cria +4; Totaliza 8
A70: Auxiliar de Administração | B70: Em vigor | D70: Efetivo | F70: Ensino Fundamental | G70: Verificar edital | I70: A-I | L70: =Planilha1!$J70-Planilha1!$K70 -> 0 | N70: Cria 30 | O70: Aumenta para 35 | AR70: Totaliza 35 | EF70: Cria +3 | FS70: Plano de carreira e vencimentos; Altera atribuições; Altera de P-15 para A-I
A71: Auxiliar de Administração - UTIL | B71: Em vigor | D71: Efetivo | F71: Ensino Fundamental | G71: Verificar edital | I71: P-15 | L71: =Planilha1!$J71-Planilha1!$K71 -> 0 | R71: Cria 2
A72: Auxiliar de Arquivo | B72: Em vigor | D72: Efetivo | F72: Ensino Fundamental | G72: Verificar edital | I72: A-I | L72: =Planilha1!$J72-Planilha1!$K72 -> 0 | AR72: Cria 2; Totaliza 2 | GJ72: Plano de Carreira, Cargos e Remuneração; Dá atribuições; Altera símbolo de vencimento para A-I
A73: Auxiliar de Biblioteca | B73: Em vigor | D73: Efetivo | F73: Ensino Fundamental | G73: Verificar edital | I73: A-I | L73: =Planilha1!$J73-Planilha1!$K73 -> 0 | N73: Cria 4 | AR73: Altera de Auxiliar de Biblioteca para Agente Administrativo ; Cria +3; Totaliza 7 | AX73: Retorna denominação de Agente Administrativo para Auxiliar de Biblioteca | HF73: Plano de Carreira e Vencimentos; Altera de P-15 para A-I
A74: Auxiliar de Comunicação | B74: Em vigor | D74: Efetivo | F74: Ensino Fundamental | G74: Verificar edital | I74: P-15 | L74: =Planilha1!$J74-Planilha1!$K74 -> 0 | N74: Cria 4 | AR74: Totaliza 4
A75: Auxiliar de Contabilidade (Acho que não existe) | B75: Em vigor | D75: Efetivo | F75: Ensino Fundamental | G75: Verificar edital | I75: P-15 | L75: =Planilha1!$J75-Planilha1!$K75 -> 0 | N75: Cria 2 | AR75: Totaliza 2
A76: Auxiliar de Creche | B76: Em vigor | D76: Efetivo | F76: Ensino Médio | G76: 40 | I76: P-22 | L76: =Planilha1!$J76-Planilha1!$K76 -> 0 | GQ76: Cria 2
A77: Auxiliar de Enfermagem | B77: Em vigor | D77: Efetivo | F77: Ensino Fundamental | G77: 30 ou 40 (vide Lei 1864/19) | I77: A-I | L77: =Planilha1!$J77-Planilha1!$K77 -> 0 | N77: Cria 22 | O77: Diminui para 12 | X77: Aumenta para 15 | AR77: Totaliza 15 | CM77: Cria +9 | DB77: Cria +3; Totaliza 27 | EJ77: Extingue 4 | FO77: Altera carga horária para 30h/semana e Regime Especial para lotados nas UESF para 40h/semana | GO77: Plano de Carreira, Cargos e Remuneração; Dá atribuições; Altera símbolo de vencimento para A-I
A78: Auxiliar de Laboratório | B78: Em vigor | D78: Efetivo | F78: Ensino Fundamental | G78: 30 | I78: A-I | L78: =Planilha1!$J78-Planilha1!$K78 -> 0 | N78: Cria 2 | AR78: Totaliza 2 | GO78: Plano de Carreira, Cargos e Remuneração; Dá atribuições; Altera símbolo de vencimento para A-I | GT78: Regulamenta carga horária em 30h/semana
A79: Auxiliar de Material | B79: Em vigor | D79: Efetivo | F79: Ensino Fundamental | G79: 40 | I79: A-I | L79: =Planilha1!$J79-Planilha1!$K79 -> 0 | N79: Cria 4 | AR79: Totaliza 4 | FV79: Altera símbolo de vencimento para A-I; O cargo passa a integrar o quadro em extinção
A80: Auxiliar de Saúde | B80: Em vigor | D80: Efetivo | F80: Ensino Fundamental | G80: Verificar edital | I80: A-I | L80: =Planilha1!$J80-Planilha1!$K80 -> 0 | N80: Cria 10 | O80: Aumenta para 12 | AR80: Totaliza 12 | GO80: Plano de Carreira, Cargos e Remuneração; Dá atribuições; Altera símbolo de vencimento para A-I
A81: Auxiliar em Saúde Bucal | B81: Em vigor | D81: Efetivo | F81: Ensino Fundamental, Curso de ASB e Registro no Conselho de Classe | G81: 20 | I81: A-I | L81: =Planilha1!$J81-Planilha1!$K81 -> 0 | N81: Cria 4 | AR81: Totaliza 4 | EH81: Altera de Auxiliar de Consultório Dentário para Auxiliar em Saúde Bucal | EK81: Cria +3 | EP81: Altera atribuições | FI81: Fixa carga horária em 20h/semana | FV81: Altera símbolo de vencimento para A-I; Dispõe sobre escolaridade | HH81: Plano de Carreira e Vencimentos; Ratifica A-I (altera valor)
A82: Bibliotecário | B82: Em vigor | D82: Efetivo | F82: Superior | G82: Verificar edital | I82: A-I | L82: =Planilha1!$J82-Planilha1!$K82 -> 0 | N82: Cria 1 | AR82: Totaliza 1 | HK82: Plano de Carreira, Cargos e Remuneração; Dá atribuições; Altera de P-34 para A-I
A83: Biólogo | B83: Em vigor | D83: Efetivo | F83: Superior | G83: Verificar edital | I83: P-34 | L83: =Planilha1!$J83-Planilha1!$K83 -> 0 | BS83: Cria 1
A84: Biomédico | B84: Em vigor | D84: Efetivo | F84: Superior | G84: Verificar edital | I84: A-I | L84: =Planilha1!$J84-Planilha1!$K84 -> 0 | BS84: Cria 1 | CM84: Cria +4 | HK84: Plano de Carreira, Cargos e Remuneração; Dá atribuições; Altera de P-34 para A-I
A85: Bioquímico | B85: Em vigor | D85: Efetivo | F85: Superior | G85: Verificar edital | I85: A-I | L85: =Planilha1!$J85-Planilha1!$K85 -> 0 | N85: Cria 1 | AO85: Fixa em 3 | AR85: Totaliza 3 | HK85: Plano de Carreira, Cargos e Remuneração; Dá atribuições; Altera de P-34 para A-I
A86: Bombeiro Hidráulico | B86: Em vigor | D86: Efetivo | F86: Ensino Fundamental Incompleto | G86: Verificar edital | I86: A-I | L86: =Planilha1!$J86-Planilha1!$K86 -> 0 | N86: Cria 2 | AR86: Totaliza 2 | FN86: Plano de Carreira, Cargos e Remuneração; Dá atribuições
A87: Calceteiro | B87: Em vigor | D87: Efetivo | F87: Ensino Fundamental Incompleto | G87: Verificar edital | I87: A-I | L87: =Planilha1!$J87-Planilha1!$K87 -> 0 | N87: Cria 8 | AI87: Aumenta para 10 | AR87: Totaliza 10 | FN87: Plano de Carreira, Cargos e Remuneração; Dá atribuições
A88: Cantineiro Escolar | B88: Em vigor | D88: Efetivo | F88: Ensino Fundamental Incompleto | G88: 30 | I88: A-I | L88: =Planilha1!$J88-Planilha1!$K88 -> 0 | N88: Cria 30 | O88: Diminui para 15 | AA88: Aumenta para 20 | AR88: Cria +8; Totaliza 28 | BF88: Cria +3; Totaliza 31 | BP88: Cria +3; Totaliza 34 | DJ88: Cria +3; Totaliza 37 | DX88: Cria +10 | EA88: Mantém 10 vagas criadas pela Lei 1604/15 | FE88: Fixa em 47 | FJ88: Fixa carga horária em 30h/semana | HE88: Plano de Carreira e Vencimentos; Altera atribuições; Altera de P-03 para A-I
A89: Carpinteiro | B89: Em vigor | D89: Efetivo | F89: Ensino Fundamental Incompleto | G89: Verificar edital | I89: A-I | L89: =Planilha1!$J89-Planilha1!$K89 -> 0 | N89: Cria 2 | AO89: Fixa em 4 | AR89: Totaliza 4 | FN89: Plano de Carreira, Cargos e Remuneração; Dá atribuições
A90: Chefe da Divisão de Almoxarifado da Secretaria Municipal de Administração | B90: Em vigor | D90: Comissão | E90: - | I90: CC-2 | L90: =Planilha1!$J90-Planilha1!$K90 -> 0 | GI90: Altera para CC-2
A91: Chefe da Divisão de Assistência Social | B91: Em vigor | D91: Comissão | E91: - | I91: CC-4 | L91: =Planilha1!$J91-Planilha1!$K91 -> 0 | ET91: Extingue
A92: Chefe da Divisão de Contabilidade do Fundo Municipal de Assistência Social | B92: Em vigor | D92: Comissão | E92: - | I92: CC-3 | L92: =Planilha1!$J92-Planilha1!$K92 -> 0 | FY92: Altera para CC-3
A93: Chefe da Divisão de Coordenação Administrativa da Secretaria - S. M. Defesa Civil e Segurança Pública | B93: Em vigor | D93: Comissão | E93: Limitado | I93: CC-3 | L93: =Planilha1!$J93-Planilha1!$K93 -> 0 | CO93: Cria 1 | GF93: Altera de CC-4 para CC-3
A94: Chefe da Divisão de Laboratório da Secretaria Municipal de Saúde | B94: Em vigor | D94: Comissão | E94: - | I94: CC-3 | L94: =Planilha1!$J94-Planilha1!$K94 -> 0 | FW94: Altera para CC-3
A95: Chefe da Divisão de Matadouro Municipal - extinto | B95: Extinto | D95: Comissão | E95: - | I95: CC-4 | L95: =Planilha1!$J95-Planilha1!$K95 -> 0 | EO95: Extingue
A96: Chefe da Divisão de Obras e Posturas | B96: Em vigor | D96: Comissão | E96: - | I96: CC-3 | L96: =Planilha1!$J96-Planilha1!$K96 -> 0 | FN96: Altera para CC-3
A97: Chefe da Divisão de Odontologia da SMS | B97: Em vigor | D97: Comissão | E97: - | I97: CC-3 | L97: =Planilha1!$J97-Planilha1!$K97 -> 0 | GF97: Altera para CC-3
A98: Chefe da Divisão de Planejamento, Projetos e Urbanismo (extinto) | B98: Extinto | D98: Comissão | E98: - | I98: CC-4 | L98: =Planilha1!$J98-Planilha1!$K98 -> 0 | GX98: Extingue
A99: Chefe da Seção de Arrecadação | B99: Em vigor | D99: Comissão | E99: - | I99: CC-3 | L99: =Planilha1!$J99-Planilha1!$K99 -> 0 | FK99: Cria | GW99: Anteriormente Chefe da Seção de Arrecadação e Dívida Ativa
A100: Chefe da Seção de Arrecadação e Dívida Ativa (Extinto) | B100: Em vigor | D100: Comissão | E100: Limitado | I100: CC-5 | L100: =Planilha1!$J100-Planilha1!$K100 -> 0 | EW100: Altera de Chefe de Seção de Registros Contábeis para Chefe de Seção de Arrecadação e Dívida Ativa | FF100: Cita | FK100: Revogado | GW100: Aparentemente divide em Chefe da Seção de Arrecadação e Chefe da Seção de Dívida Ativa
...
